cache.py
config.py
policy.py
secscan.py
secscan_cli-1.4.1.data/data/share/man/man1/secscan.1
secscan_cli-1.4.1.dist-info/licenses/AUTHORS
secscan_cli-1.4.1.dist-info/licenses/LICENSE
secscan_cli-1.4.1.dist-info/METADATA
secscan_cli-1.4.1.dist-info/WHEEL
secscan_cli-1.4.1.dist-info/entry_points.txt
secscan_cli-1.4.1.dist-info/top_level.txt
secscan_cli-1.4.1.dist-info/RECORD
