Metadata-Version: 2.4
Name: secscan-cli
Version: 1.4.1
Summary: A multi-language dependency vulnerability scanner supporting JavaScript, Python, and Go
Home-page: https://github.com/deosha/secscan
Author: Deo Shankar
Author-email: Deo Shankar <deoshankar89@gmail.com>
License: MIT
Project-URL: Homepage, https://github.com/deosha/secscan
Project-URL: Bug Tracker, https://github.com/deosha/secscan/issues
Project-URL: Documentation, https://github.com/deosha/secscan#readme
Project-URL: Source Code, https://github.com/deosha/secscan
Keywords: security,vulnerability,scanner,dependencies,npm,pip,go,osv
Classifier: Development Status :: 4 - Beta
Classifier: Intended Audience :: Developers
Classifier: Topic :: Security
Classifier: Topic :: Software Development :: Quality Assurance
Classifier: Programming Language :: Python :: 3
Classifier: Programming Language :: Python :: 3.7
Classifier: Programming Language :: Python :: 3.8
Classifier: Programming Language :: Python :: 3.9
Classifier: Programming Language :: Python :: 3.10
Classifier: Programming Language :: Python :: 3.11
Classifier: Programming Language :: Python :: 3.12
Classifier: Operating System :: OS Independent
Classifier: Environment :: Console
Requires-Python: >=3.7
License-File: LICENSE
License-File: AUTHORS
Requires-Dist: requests>=2.25.0
Requires-Dist: pyyaml>=5.4.0
Provides-Extra: dev
Requires-Dist: pytest>=6.0.0; extra == "dev"
Requires-Dist: pytest-cov>=2.0.0; extra == "dev"
Requires-Dist: black>=22.0.0; extra == "dev"
Requires-Dist: flake8>=4.0.0; extra == "dev"
Requires-Dist: mypy>=0.900; extra == "dev"
Dynamic: author
Dynamic: home-page
Dynamic: license-file
Dynamic: requires-python
